agentos_sdk/__init__.py
agentos_sdk/banner.py
agentos_sdk/main.py
agentos_sdk/prompt.py
agentos_sdk/rag.py
agentos_sdk/tools.py
agentos_sdk/workspace.py
agentos_sdk-0.0.3.dist-info/LICENSE
agentos_sdk-0.0.3.dist-info/METADATA
agentos_sdk-0.0.3.dist-info/WHEEL
agentos_sdk-0.0.3.dist-info/RECORD
