Metadata-Version: 2.3
Name: agentos-sdk
Version: 0.0.3
Summary: AgentOS - TGSC
License: MIT
Keywords: artificial intelligence,deep learning,optimizers,Prompt Engineering,swarms,agents,llms,transformers,multi-agent,swarms of agents,Enterprise-Grade Agents,Production-Grade Agents,Agents,Multi-Grade-Agents,Swarms,Transformers,LLMs,Prompt Engineering,Agents,Generative Agents,Generative AI,Agent Marketplace,Agent Store,quant,finance,algorithmic trading,portfolio optimization,risk management,financial modeling,machine learning for finance,natural language processing for finance
Author: Kye Gomez
Author-email: kye@apac.ai
Requires-Python: >=3.10,<4.0
Classifier: Development Status :: 4 - Beta
Classifier: Intended Audience :: Developers
Classifier: License :: OSI Approved :: MIT License
Classifier: Programming Language :: Python :: 3
Classifier: Programming Language :: Python :: 3.10
Classifier: Programming Language :: Python :: 3.11
Classifier: Programming Language :: Python :: 3.12
Classifier: Programming Language :: Python :: 3.13
Classifier: Topic :: Scientific/Engineering :: Artificial Intelligence
Requires-Dist: beautifulsoup4
Requires-Dist: browser-use
Requires-Dist: chromadb
Requires-Dist: claude-code-sdk
Requires-Dist: google-cloud-aiplatform
Requires-Dist: langchain-openai
Requires-Dist: litellm
Requires-Dist: pandas
Requires-Dist: pypdf2
Requires-Dist: sentence-transformers
Requires-Dist: swarms
Requires-Dist: torch
Requires-Dist: transformers
Project-URL: Documentation, https://docs.swarms.world
Project-URL: Homepage, https://github.com/The-Swarm-Corporation/AgentOS
Project-URL: Repository, https://github.com/The-Swarm-Corporation/AgentOS
